LICENSE
MANIFEST.in
README.md
setup.cfg
setup.py
version.py
geno_sugar/__init__.py
geno_sugar/_sh.py
geno_sugar/_testit.py
geno_sugar/conftest.py
geno_sugar/geno_queue.py
geno_sugar/preprocess.py
geno_sugar/utils.py
geno_sugar.egg-info/PKG-INFO
geno_sugar.egg-info/SOURCES.txt
geno_sugar.egg-info/dependency_links.txt
geno_sugar.egg-info/requires.txt
geno_sugar.egg-info/top_level.txt
geno_sugar.egg-info/zip-safe
geno_sugar/test/__init__.py
geno_sugar/test/test_preprocess.py