Metadata-Version: 2.1
Name: geno-sugar
Version: 0.0.1
Summary: Utility functions to read bed and bgen files
Home-page: https://github.com/limix/geno-sugar
Author: Francesco Paolo Casale
Author-email: casale@ebi.ac.uk
Maintainer: Francesco Paolo Casale
Maintainer-email: casale@ebi.ac.uk
License: APACHE
Download-URL: https://github.com/limix/geno-sugar
Keywords: GWAS,LMM
Platform: Windows
Platform: MacOS
Platform: Linux
Classifier: Development Status :: 5 - Production/Stable
Classifier: License :: OSI Approved :: Apache Software License
Classifier: Operating System :: OS Independent
Classifier: Programming Language :: Python
